psnawp_api/__init__.py
psnawp_api/core/__init__.py
psnawp_api/core/authenticator.py
psnawp_api/core/psnawp_exceptions.py
psnawp_api/core/request_builder.py
psnawp_api/models/__init__.py
psnawp_api/models/client.py
psnawp_api/models/game_title.py
psnawp_api/models/group.py
psnawp_api/models/listing/__init__.py
psnawp_api/models/listing/pagination_iterator.py
psnawp_api/models/search.py
psnawp_api/models/title_stats.py
psnawp_api/models/trophies/__init__.py
psnawp_api/models/trophies/trophy.py
psnawp_api/models/trophies/trophy_constants.py
psnawp_api/models/trophies/trophy_group.py
psnawp_api/models/trophies/trophy_summary.py
psnawp_api/models/trophies/trophy_titles.py
psnawp_api/models/trophies/utility_functions.py
psnawp_api/models/user.py
psnawp_api/psnawp.py
psnawp_api/py.typed
psnawp_api/utils/__init__.py
psnawp_api/utils/endpoints.py
psnawp_api/utils/misc.py
psnawp_async-0.0.5.dist-info/AUTHORS.md
psnawp_async-0.0.5.dist-info/LICENSE.md
psnawp_async-0.0.5.dist-info/LICENSES/LICENSE-PSN_PHP.md
psnawp_async-0.0.5.dist-info/LICENSES/LICENSE-PlayStationNetwork_API.md
psnawp_async-0.0.5.dist-info/LICENSES/LICENSE-PlayStation_Trophies.md
psnawp_async-0.0.5.dist-info/METADATA
psnawp_async-0.0.5.dist-info/WHEEL
psnawp_async-0.0.5.dist-info/RECORD
