Metadata-Version: 2.1
Name: PSNAWP_ASYNC
Version: 0.0.5
Summary: Async Python API Wrapper for PlayStation Network API
License: MIT
Keywords: PSN,PlayStation
Author: jackjpowell
Author-email: jackjpowell@gmail.com
Requires-Python: >=3.9,<4.0
Classifier: Development Status :: 4 - Beta
Classifier: Intended Audience :: Developers
Classifier: License :: OSI Approved :: MIT License
Classifier: Operating System :: OS Independent
Classifier: Programming Language :: Python
Classifier: Programming Language :: Python :: 3
Classifier: Programming Language :: Python :: 3.9
Classifier: Programming Language :: Python :: 3.10
Classifier: Programming Language :: Python :: 3.11
Classifier: Programming Language :: Python :: 3.12
Classifier: Topic :: Software Development :: Libraries :: Python Modules
Requires-Dist: attrs (>=23.1.0,<24.0.0)
Requires-Dist: requests (>=2.31.0,<3.0.0)
Requires-Dist: typing-extensions (>=4.11.0,<5.0.0)
